cbfax/cbf.py
cbfax/dynamics.py
cbfax/plotting.py
cbfax-0.0.1.dist-info/METADATA
cbfax-0.0.1.dist-info/WHEEL
cbfax-0.0.1.dist-info/top_level.txt
cbfax-0.0.1.dist-info/RECORD
